{
    "client": "Thunder Client",
    "collectionName": "mascotas Evan",
    "dateExported": "2024-02-23T14:30:34.844Z",
    "version": "1.1",
    "folders": [],
    "requests": [
        {
            "_id": "2646d7fd-c129-4acf-a0b6-f3fe387223ea",
            "colId": "9fad51d6-1980-41bc-b3e0-f8fa3c11e2ce",
            "containerId": "",
            "name": "post mascota",
            "url": "http://localhost:3000/api/mascotas",
            "method": "POST",
            "sortNum": 10000,
            "created": "2024-02-23T13:52:11.679Z",
            "modified": "2024-02-23T13:55:03.297Z",
            "headers": [],
            "params": [],
            "body": {
                "type": "json",
                "raw": "{\n  \"nombre\": \"Tufo\",\n  \"edad\": \"13 años\",\n  \"clase\": \"Perrito con sarna\",\n  \"adoptado\": \"ADOPTADO\"\n}",
                "form": []
            },
            "tests": []
        },
        {
            "_id": "43d8c462-abb5-47ac-b68b-c26b8cc2bf29",
            "colId": "9fad51d6-1980-41bc-b3e0-f8fa3c11e2ce",
            "containerId": "",
            "name": "GetMascotaById",
            "url": "http://localhost:3000/api/mascotas/65d8a4e392c3ad6d9a8191bc",
            "method": "GET",
            "sortNum": 20000,
            "created": "2024-02-23T14:03:33.036Z",
            "modified": "2024-02-23T14:03:33.036Z",
            "headers": [],
            "params": [],
            "tests": []
        }
    ]
}